pynball_rl/__init__.py
pynball_rl/__main__.py
pynball_rl/ball.py
pynball_rl/configs/corridor_2d_config.toml
pynball_rl/configs/easy_2d_config.toml
pynball_rl/configs/easy_config.toml
pynball_rl/configs/four_rooms_2d_config.toml
pynball_rl/configs/hard_2d_config.toml
pynball_rl/configs/hard_config.toml
pynball_rl/configs/very_easy_config.toml
pynball_rl/obstacle.py
pynball_rl/point.py
pynball_rl/polygon_obstacle.py
pynball_rl/pynball_env.py
pynball_rl/rollout.py
pynball_rl/target.py
pynball_rl/utils.py
pynball_rl/viewer.py
pynball_rl-1.0.2.dist-info/LICENSE
pynball_rl-1.0.2.dist-info/METADATA
pynball_rl-1.0.2.dist-info/WHEEL
pynball_rl-1.0.2.dist-info/RECORD
