Metadata-Version: 2.1
Name: pynball-rl
Version: 1.0.2
Summary: A python implementation of the classic reinforcement learning domain pinball: http://irl.cs.brown.edu/pinball/
Home-page: https://github.com/tmssmith/pynball-rl
License: MIT
Author: Tom Smith
Author-email: tmssmith@gmail.com
Requires-Python: >=3.10,<4.0
Classifier: License :: OSI Approved :: MIT License
Classifier: Programming Language :: Python :: 3
Classifier: Programming Language :: Python :: 3.10
Classifier: Programming Language :: Python :: 3.11
Classifier: Programming Language :: Python :: 3.12
Requires-Dist: matplotlib (>=3.8.3,<4.0.0)
Requires-Dist: pygame (>=2.5.2,<3.0.0)
Requires-Dist: tomli (>=2.0.1,<3.0.0) ; python_version < "3.11"
Project-URL: Repository, https://github.com/tmssmith/pynball-rl
